netizenship.py
netizenship-0.2.3.dist-info/entry_points.txt
netizenship-0.2.3.dist-info/LICENSE
netizenship-0.2.3.dist-info/WHEEL
netizenship-0.2.3.dist-info/METADATA
netizenship-0.2.3.dist-info/RECORD
