Metadata-Version: 2.1
Name: netizenship
Version: 0.2.3
Summary: Tool to check the username with popular websites for membership
Home-page: https://github.com/rahulrajpl/netizenship
Author: Rahul Raj
Author-email: rahulrajpl@gmail.com
Requires-Python: >=3.7,<4.0
Classifier: Programming Language :: Python :: 3
Classifier: Programming Language :: Python :: 3.7
Classifier: Programming Language :: Python :: 3.8
Requires-Dist: beautifulsoup4 (>=4.8.2,<5.0.0)
Requires-Dist: importlib_metadata (>=1.4.0,<2.0.0)
Requires-Dist: pyfiglet (>=0.8.post1,<0.9)
Requires-Dist: requests (>=2.22.0,<3.0.0)
Requires-Dist: termcolor (>=1.1.0,<2.0.0)
Project-URL: Documentation, https://github.com/rahulrajpl/netizenship/blob/master/README.md
